aij_team/__init__.py
aij_team/functions.py
aij_team-1.0.0.dist-info/METADATA
aij_team-1.0.0.dist-info/WHEEL
aij_team-1.0.0.dist-info/top_level.txt
aij_team-1.0.0.dist-info/RECORD
