Metadata-Version: 2.1
Name: aij_team
Version: 1.0.0
Summary: A library that does some math-based equations
Author: AIJ Team
Author-email: python.bot.0909@gmail.com
Classifier: Programming Language :: Python :: 3
Classifier: License :: OSI Approved :: MIT License
Classifier: Operating System :: OS Independent
Requires-Python: >=3.6
